kagaconf/__init__.py
kagaconf-0.1.3.dist-info/LICENSE
kagaconf-0.1.3.dist-info/METADATA
kagaconf-0.1.3.dist-info/WHEEL
kagaconf-0.1.3.dist-info/top_level.txt
kagaconf-0.1.3.dist-info/RECORD
