Metadata-Version: 2.1
Name: kagaconf
Version: 0.1.3
Summary: Simple Python configuration loading interface I wrote for use in KAGAYAKI
Home-page: https://github.com/ilonachan/kagaconf
Author: ilonachan
Author-email: nagato_ilona@protonmail.com
License: MIT
Keywords: config
Platform: UNKNOWN
Classifier: Development Status :: 1 - Planning
Classifier: License :: OSI Approved :: MIT License
Classifier: Programming Language :: Python :: 3
Classifier: Programming Language :: Python :: 3.10
License-File: LICENSE
Requires-Dist: PyYAML
